{
    "$schema": "https://vega.github.io/schema/vega-lite/v5.json",
    "background": "#e9eef1",
    "title": "Women titled players by country (grouped by title)",
    "width":625,
    "height": 220,
    "config": {
        "view": {"stroke": "transparent"}    
    },
    "data": {
        "url": "rated_player_count.csv",
        "format": {"type": "csv"}
    },
    "transform": [
        {
            "fold": ["WCM_count", "WFM_count", "WIM_count", "WGM_count"],
            "as": ["Title", "Count"]
        },
        {
            "filter": "indexof(['Russia', 'India', 'United States of America', 'China', 'Poland', 'Germany', 'Australia'], datum.Country) >= 0"
        }
    ],
    "layer": [
        {
            "mark": {"type": "bar", "size": 2},
            "encoding": {
                "xOffset": {
                    "field": "Title",
                    "sort": ["WCM_count","WFM_count","WIM_count","WGM_count"]
                }
            }
        },
        {
            "mark": {"type": "circle"},
            "encoding": {
                "xOffset": {
                    "field": "Title",
                    "sort": ["WCM_count","WFM_count","WIM_count","WGM_count"]
                }
            }
        },
        {
            "mark": {"type": "text", "dy": -10, "fontSize": 10},
            "encoding": {
                "text": {"field": "Count", "type": "quantitative"},
                "xOffset": {
                    "field": "Title",
                    "sort": ["WCM_count","WFM_count","WIM_count","WGM_count"]
                }
            }
        }
    ],
    "encoding": {
        "x": {
            "field": "Country",
            "type": "nominal",
            "axis": {
                "labelAngle": 0
            }
        },
        "y": {
            "field": "Count", 
            "type": "quantitative", 
            "axis": {"title": "Count", "titleAngle": 0, "titleX": -40}
        },
        "color": {
            "field": "Title", 
            "type": "nominal", 
            "legend": {"title": "Title"}, 
            "sort": ["WCM_count","WFM_count","WIM_count","WGM_count"]
        },
        "tooltip": [
            {"field": "Country", "type": "nominal"},
            {"field": "Title", "type": "nominal"},
            {"field": "Count", "type": "quantitative"}
        ]
    }
}